cohesivm/__init__.py
cohesivm/channels.py
cohesivm/config.py
cohesivm/data_stream.py
cohesivm/database.py
cohesivm/experiment.py
cohesivm/gui.py
cohesivm/plots.py
cohesivm/progressbar.py
cohesivm/serial_communication.py
cohesivm/analysis/__init__.py
cohesivm/analysis/iv.py
cohesivm/devices/__init__.py
cohesivm/devices/agilent/Agilent4156C.py
cohesivm/devices/agilent/Agilent4284A.py
cohesivm/devices/agilent/__init__.py
cohesivm/devices/ossila/OssilaX200.py
cohesivm/devices/ossila/__init__.py
cohesivm/interfaces/__init__.py
cohesivm/interfaces/ma8x8.py
cohesivm/interfaces/trivial.py
cohesivm/measurements/__init__.py
cohesivm/measurements/cv.py
cohesivm/measurements/iv.py
cohesivm-1.0.1.dist-info/METADATA
cohesivm-1.0.1.dist-info/WHEEL
cohesivm-1.0.1.dist-info/licenses/LICENSE
cohesivm-1.0.1.dist-info/RECORD
