Metadata-Version: 2.4
Name: cohesivm
Version: 1.0.1
Summary: Combinatorial h+/e- Sample Investigation using Voltaic Measurements
Project-URL: Homepage, https://github.com/mxwalbert/cohesivm
Project-URL: Documentation, https://cohesivm.readthedocs.io/en/latest
Project-URL: Issues, https://github.com/mxwalbert/cohesivm/issues
Author-email: Maximilian Wolf <maximilian.wolf@ait.ac.at>, Selina Götz <selina.goetz@ait.ac.at>, "Georg K.H. Madsen" <georg.madsen@tuwien.ac.at>, Theodoros Dimopoulos <theodoros.dimopoulos@ait.ac.at>
License-File: LICENSE
Classifier: License :: OSI Approved :: MIT License
Classifier: Operating System :: OS Independent
Classifier: Programming Language :: Python :: 3
Classifier: Topic :: Scientific/Engineering :: Human Machine Interfaces
Requires-Python: >=3.9
Requires-Dist: h5py~=3.8
Requires-Dist: matplotlib~=3.7
Requires-Dist: numpy~=1.21
Requires-Dist: tqdm~=4.65
Provides-Extra: agilent
Requires-Dist: pyvisa~=1.13; extra == 'agilent'
Provides-Extra: dev
Requires-Dist: bqplot~=0.12; extra == 'dev'
Requires-Dist: pyserial~=3.5; extra == 'dev'
Requires-Dist: pytest~=7.3; extra == 'dev'
Requires-Dist: pyvisa~=1.13; extra == 'dev'
Requires-Dist: xtralien~=2.10; extra == 'dev'
Provides-Extra: full
Requires-Dist: bqplot~=0.12; extra == 'full'
Requires-Dist: pyserial~=3.5; extra == 'full'
Requires-Dist: pyvisa~=1.13; extra == 'full'
Requires-Dist: xtralien~=2.10; extra == 'full'
Provides-Extra: gui
Requires-Dist: bqplot~=0.12; extra == 'gui'
Provides-Extra: ma8x8
Requires-Dist: pyserial~=3.5; extra == 'ma8x8'
Provides-Extra: ossila
Requires-Dist: xtralien~=2.10; extra == 'ossila'
